clr_scrn/__init__.py
clr_scrn/clear.py
clr_scrn-0.1.3.dist-info/LICENSE
clr_scrn-0.1.3.dist-info/METADATA
clr_scrn-0.1.3.dist-info/WHEEL
clr_scrn-0.1.3.dist-info/top_level.txt
clr_scrn-0.1.3.dist-info/RECORD
